rocketisp/HTMLTags.py
rocketisp/HTML_supt.py
rocketisp/InterpProp_scipy.py
rocketisp/__init__.py
rocketisp/_version.py
rocketisp/cast.py
rocketisp/efficiencies.py
rocketisp/geometry.py
rocketisp/goldSearch.py
rocketisp/injector.py
rocketisp/model_summ.py
rocketisp/mr_range.py
rocketisp/parse_docstring.py
rocketisp/rocket_isp.py
rocketisp/stream_tubes.py
rocketisp/unit_conv_data.py
rocketisp/utils.py
rocketisp/efficiency/__init__.py
rocketisp/efficiency/calc_full_pcentLossBL.npz
rocketisp/efficiency/calc_full_pcentLossBL.py
rocketisp/efficiency/calc_full_pcentLossDiv.npz
rocketisp/efficiency/calc_full_pcentLossDiv.py
rocketisp/efficiency/calc_noz_kinetics.py
rocketisp/efficiency/effBL_NASA_SP8120.py
rocketisp/efficiency/eff_divergence.py
rocketisp/efficiency/eff_pulsing.py
rocketisp/efficiency/eff_vaporization.py
rocketisp/efficiency/get_elements.py
rocketisp/efficiency/fracKinODK/__init__.py
rocketisp/efficiency/fracKinODK/calc_All_fracKin.npz
rocketisp/efficiency/fracKinODK/calc_All_fracKin.py
rocketisp/efficiency/fracKinODK/calc_CCLFHN_fracKin.npz
rocketisp/efficiency/fracKinODK/calc_CCLFHN_fracKin.py
rocketisp/efficiency/fracKinODK/calc_CFHNO_fracKin.npz
rocketisp/efficiency/fracKinODK/calc_CFHNO_fracKin.py
rocketisp/efficiency/fracKinODK/calc_CFHN_fracKin.npz
rocketisp/efficiency/fracKinODK/calc_CFHN_fracKin.py
rocketisp/efficiency/fracKinODK/calc_CFHO_fracKin.npz
rocketisp/efficiency/fracKinODK/calc_CFHO_fracKin.py
rocketisp/efficiency/fracKinODK/calc_CHNO_fracKin.npz
rocketisp/efficiency/fracKinODK/calc_CHNO_fracKin.py
rocketisp/efficiency/fracKinODK/calc_CHO_fracKin.npz
rocketisp/efficiency/fracKinODK/calc_CHO_fracKin.py
rocketisp/efficiency/fracKinODK/calc_CLFHN_fracKin.npz
rocketisp/efficiency/fracKinODK/calc_CLFHN_fracKin.py
rocketisp/efficiency/fracKinODK/calc_CLFH_fracKin.npz
rocketisp/efficiency/fracKinODK/calc_CLFH_fracKin.py
rocketisp/efficiency/fracKinODK/calc_FHNO_fracKin.npz
rocketisp/efficiency/fracKinODK/calc_FHNO_fracKin.py
rocketisp-0.1.11.dist-info/AUTHORS.rst
rocketisp-0.1.11.dist-info/LICENSE.txt
rocketisp-0.1.11.dist-info/METADATA
rocketisp-0.1.11.dist-info/WHEEL
rocketisp-0.1.11.dist-info/entry_points.txt
rocketisp-0.1.11.dist-info/top_level.txt
rocketisp-0.1.11.dist-info/RECORD
