Metadata-Version: 2.1
Name: rocketisp
Version: 0.1.11
Summary: RocketIsp calculates delivered Isp for liquid rocket thrust chambers.
Home-page: http://rocketisp.readthedocs.org/en/latest/
Author: Charlie Taylor
Author-email: cet@appliedpython.com
License: GPL-3
Download-URL: https://github.com/sonofeft/RocketIsp
Requires-Dist: numpy
Requires-Dist: scipy
Requires-Dist: rocketcea
Requires-Dist: rocketprops
Provides-Extra: dev
Requires-Dist: check-manifest ; extra == 'dev'
Provides-Extra: test
Requires-Dist: coverage ; extra == 'test'
